Metadata-Version: 2.4
Name: sunbeamlib
Version: 5.2.2
Summary: A snakemake utility for metagenomic sequencing analysis
Author: Erik Clarke, Charlie Bushman, Chunyu Zhao, Jesse Connell, Louis Taylor, Kyle Bittinger
Maintainer-email: Charlie Bushman <ctbushman@gmail.com>
Project-URL: Homepage, https://github.com/sunbeam-labs/sunbeam
Project-URL: Bug Reports, https://github.com/sunbeam-labs/sunbeam/issues
Project-URL: Docs, https://sunbeam.readthedocs.io/en/stable/
Project-URL: Source, https://github.com/sunbeam-labs/sunbeam
Classifier: Programming Language :: Python :: 3
Classifier: Programming Language :: Python :: 3.11
Classifier: Programming Language :: Python :: 3.12
Classifier: Programming Language :: Python :: 3.13
Classifier: Programming Language :: Python :: 3 :: Only
Requires-Python: >=3.11
Requires-Dist: snakemake==9.9.0
Requires-Dist: more-itertools==10.7.0
Requires-Dist: pyyaml==6.0.2
Requires-Dist: pandas==2.3.1
Provides-Extra: dev
Requires-Dist: black==24.10.0; extra == "dev"
Requires-Dist: snakefmt==0.11.0; extra == "dev"
Requires-Dist: pytest==8.4.1; extra == "dev"
